fava_miler/MANIFEST.in
fava_miler/__init__.py
fava_miler/libmiler.py
fava_miler/miler.py
fava_miler/test_libmiler.py
fava_miler/common/__init__.py
fava_miler/common/beancountinvestorapi.py
fava_miler/common/clicommon.py
fava_miler/common/favainvestorapi.py
fava_miler/templates/Miler.html
fava_miler-0.3.0.dist-info/LICENSE
fava_miler-0.3.0.dist-info/METADATA
fava_miler-0.3.0.dist-info/WHEEL
fava_miler-0.3.0.dist-info/entry_points.txt
fava_miler-0.3.0.dist-info/top_level.txt
fava_miler-0.3.0.dist-info/RECORD
