Metadata-Version: 2.1
Name: fava-miler
Version: 0.3.0
Summary: Show expiry of airline miles, rewards points
Home-page: https://github.com/redstreet/fava_miler
Author: Red S
Author-email: redstreet@users.noreply.github.com
License: GPL-3.0
Keywords: fava beancount accounting investment
Classifier: Development Status :: 3 - Alpha
Classifier: Intended Audience :: Financial and Insurance Industry
Classifier: License :: OSI Approved :: GNU General Public License v3 (GPLv3)
Classifier: Natural Language :: English
Classifier: Programming Language :: Python :: 3 :: Only
Classifier: Programming Language :: Python :: 3.6
Classifier: Topic :: Internet :: WWW/HTTP :: Dynamic Content
Classifier: Topic :: Office/Business :: Financial :: Accounting
Classifier: Topic :: Office/Business :: Financial :: Investment
License-File: LICENSE
Requires-Dist: beancount (>=2.3.1)
Requires-Dist: fava (>=1.23)
Requires-Dist: Click
